{
  "authorDailyContributionsMap": {
    "Ederporto": [
      {
        "insertions": 64,
        "deletions": 37,
        "date": "2019-12-15",
        "commitResults": [
          {
            "hash": "ab2d9c2862af18b06a39dede6abf90dcb00baeb5",
            "messageTitle": "Translated using Weblate (Portuguese (Brazil))",
            "messageBody": "Currently translated at 100.0% (735 of 735 strings)\n\nTranslation: OpenRefine/Translations\nTranslate-URL: https://hosted.weblate.org/projects/openrefine/translations/pt_BR/\n",
            "insertions": 64,
            "deletions": 37
          }
        ]
      }
    ],
    "Antonin Delpeuch": [
      {
        "insertions": 103,
        "deletions": 9,
        "date": "2019-12-21",
        "commitResults": [
          {
            "hash": "1355a373c9063cd53025bbdf30f8c1509f4d495d",
            "messageTitle": "Mock HTTP calls in EntityCache",
            "messageBody": "",
            "insertions": 103,
            "deletions": 9
          }
        ]
      },
      {
        "insertions": 10,
        "deletions": 27,
        "date": "2019-12-22",
        "commitResults": [
          {
            "hash": "02a8f411e442a9bf3348fa67220e8067e32d89b4",
            "messageTitle": "Update Apache POI to 4.1.1, for #949",
            "messageBody": "",
            "insertions": 2,
            "deletions": 2
          },
          {
            "hash": "8ceaeb0743520b83f8049bf8ca131fe7115951a0",
            "messageTitle": "Use jQuery.submit to bind form to login",
            "messageBody": "",
            "insertions": 8,
            "deletions": 25
          }
        ]
      },
      {
        "insertions": 64,
        "deletions": 104,
        "date": "2019-12-24",
        "commitResults": [
          {
            "hash": "ad261109beb3ce3e7e9f037297c7fedd4a38a55f",
            "messageTitle": "Fetch default recon service in background silently. Fixes #1665",
            "messageBody": "",
            "insertions": 12,
            "deletions": 7
          },
          {
            "hash": "2e1d5402ea5e933aaad4b4e2046cbc5096b5c102",
            "messageTitle": "Add CORS support with JSONP fallback. Closes #2260",
            "messageBody": "",
            "insertions": 52,
            "deletions": 14
          },
          {
            "hash": "63bb9e31356093d109f15978b39f2724db29c50d",
            "messageTitle": "Remove unused suggest-4_3.min.js",
            "messageBody": "",
            "insertions": 0,
            "deletions": 83
          }
        ]
      },
      {
        "insertions": 96,
        "deletions": 17,
        "date": "2019-12-25",
        "commitResults": [
          {
            "hash": "fe57897e8e166030fb66160349dfa213f749cf57",
            "messageTitle": "Fix Wikidata login CSRF issue. Closes #2228.",
            "messageBody": "",
            "insertions": 12,
            "deletions": 2
          },
          {
            "hash": "78853f8fb22b4ae31de7f7c606de87c03ee2e901",
            "messageTitle": "More robust URI detection in tabular exporter. Closes #2213.",
            "messageBody": "",
            "insertions": 36,
            "deletions": 6
          },
          {
            "hash": "08e175dc66c58f393ed9b8c720ad8faf503cfdbe",
            "messageTitle": "Fix NPE in expresion logging. Closes #2086.",
            "messageBody": "",
            "insertions": 38,
            "deletions": 5
          },
          {
            "hash": "7593d5484d1f7d69dc65385b9d6b91c9b0f39a22",
            "messageTitle": "Add Hyperlink to cell in Excel importer, with fallback to String, for #2213",
            "messageBody": "",
            "insertions": 10,
            "deletions": 4
          }
        ]
      },
      {
        "insertions": 7,
        "deletions": 0,
        "date": "2019-12-27",
        "commitResults": [
          {
            "hash": "539a04e49611ce60bd2952d68819632630fb3525",
            "messageTitle": "Fix Coveralls Maven plugin, closes #2266",
            "messageBody": "",
            "insertions": 7,
            "deletions": 0
          }
        ]
      },
      {
        "insertions": 32,
        "deletions": 707,
        "date": "2019-12-31",
        "commitResults": [
          {
            "hash": "fe5871bd51caeed7c79403645fe10d4c630788b6",
            "messageTitle": "Remove Fusion Tables support in gdata extension. Closes #2113.",
            "messageBody": "",
            "insertions": 12,
            "deletions": 694
          },
          {
            "hash": "6dc79d965d16e4abcbfbaf080930602a6a608080",
            "messageTitle": "Use state to keep redirect URI constant",
            "messageBody": "",
            "insertions": 20,
            "deletions": 13
          }
        ]
      },
      {
        "insertions": 6,
        "deletions": 12,
        "date": "2020-01-04",
        "commitResults": [
          {
            "hash": "a4c4a207673ef1465c0713a7c6661f1dc071e7a0",
            "messageTitle": "Fix Google Sheets and Google Drive export",
            "messageBody": "",
            "insertions": 6,
            "deletions": 12
          }
        ]
      },
      {
        "insertions": 74,
        "deletions": 36,
        "date": "2020-01-06",
        "commitResults": [
          {
            "hash": "904129d0f7003a61c47425309d6b403b79085fc5",
            "messageTitle": "Fix other NPE in expression logging, for #2264",
            "messageBody": "",
            "insertions": 42,
            "deletions": 7
          },
          {
            "hash": "1046c38727a70192d48e677656875d386b644b12",
            "messageTitle": "Fix Wikidata login form, closes #2194",
            "messageBody": "",
            "insertions": 13,
            "deletions": 10
          },
          {
            "hash": "ae41348e00cec2644ddb4cee24db4a67c16ffd92",
            "messageTitle": "Fix bug with TODAY in Wikidata schema",
            "messageBody": "",
            "insertions": 2,
            "deletions": 2
          },
          {
            "hash": "d77d54803f4fec3b76eb84bff588a08c4e0c105a",
            "messageTitle": "Fix Wikidata TODAY test",
            "messageBody": "",
            "insertions": 2,
            "deletions": 2
          },
          {
            "hash": "e62bb7ac0e80049fb3d6d47b619de92580f9162d",
            "messageTitle": "Set version to 3.3-rc1",
            "messageBody": "",
            "insertions": 15,
            "deletions": 15
          }
        ]
      },
      {
        "insertions": 17,
        "deletions": 17,
        "date": "2020-01-08",
        "commitResults": [
          {
            "hash": "352d209b9f30702c897078f5e1d3797db1100c50",
            "messageTitle": "Lowercase \"email\"",
            "messageBody": "",
            "insertions": 2,
            "deletions": 2
          },
          {
            "hash": "faece760f65d18ac398759c6effbaa30ab21ffeb",
            "messageTitle": "Set version to 3.3-SNAPSHOT",
            "messageBody": "",
            "insertions": 15,
            "deletions": 15
          }
        ]
      }
    ],
    "Hosted Weblate": [],
    "Bhanu Gupta": [
      {
        "insertions": 22,
        "deletions": 3,
        "date": "2019-12-21",
        "commitResults": [
          {
            "hash": "cfc962668c606ea60116964a2cb816c38d2c8095",
            "messageTitle": "Added fuctionality of form submit by enter key in Wikidata Login dialogue",
            "messageBody": "",
            "insertions": 22,
            "deletions": 3
          }
        ]
      },
      {
        "insertions": 31,
        "deletions": 30,
        "date": "2019-12-22",
        "commitResults": [
          {
            "hash": "acba3e59ae2f85dc9b5c4761766e190b1e3bced7",
            "messageTitle": "Enter key press issues resolved",
            "messageBody": "",
            "insertions": 30,
            "deletions": 29
          },
          {
            "hash": "7c06afc3bbe753b747bcb3bdeea14e4f9423176f",
            "messageTitle": "Enter key press issues resolved",
            "messageBody": "",
            "insertions": 1,
            "deletions": 1
          }
        ]
      }
    ],
    "jamessspanggg": [
      {
        "insertions": 6,
        "deletions": 2,
        "date": "2020-01-07",
        "commitResults": [
          {
            "hash": "5afd93e2d157e7a2e02b00d99dcd502a4ae11e70",
            "messageTitle": "Standardise \u0027edit\u0027 cell dialogue with \u0027toNumber()\u0027 behavior",
            "messageBody": "",
            "insertions": 5,
            "deletions": 1
          },
          {
            "hash": "c2d72c6236a47ad1b340c311ada4ed42263bb6d0",
            "messageTitle": "Translate sort link using i18n",
            "messageBody": "",
            "insertions": 1,
            "deletions": 1
          }
        ]
      },
      {
        "insertions": 41,
        "deletions": 2,
        "date": "2020-01-08",
        "commitResults": [
          {
            "hash": "fc97b3f188836a5da2fe82e818231bc9c5be2f94",
            "messageTitle": "Fix mistake of translating wrong word",
            "messageBody": "",
            "insertions": 1,
            "deletions": 1
          },
          {
            "hash": "67b62c5c1679ecbdf82a93b15646b26f7fc03f8e",
            "messageTitle": "EditOneCellCommandTests: Add number parsing tests",
            "messageBody": "",
            "insertions": 40,
            "deletions": 1
          }
        ]
      }
    ],
    "Isao Matsunami": [
      {
        "insertions": 3,
        "deletions": 2,
        "date": "2020-01-07",
        "commitResults": [
          {
            "hash": "685faa304d97f118956f4ae7512f38eedd97e97a",
            "messageTitle": "Translated using Weblate (Japanese)",
            "messageBody": "Currently translated at 100.0% (44 of 44 strings)\n\nTranslation: OpenRefine/gdata\nTranslate-URL: https://hosted.weblate.org/projects/openrefine/gdata/ja/\n",
            "insertions": 3,
            "deletions": 2
          }
        ]
      }
    ],
    "Luca Martinelli": [
      {
        "insertions": 75,
        "deletions": 36,
        "date": "2020-01-10",
        "commitResults": [
          {
            "hash": "d1d320f0c07c67ba2e382558cd97e0028995290d",
            "messageTitle": "Translated using Weblate (Italian)",
            "messageBody": "Currently translated at 100.0% (735 of 735 strings)\n\nTranslation: OpenRefine/Translations\nTranslate-URL: https://hosted.weblate.org/projects/openrefine/translations/it/\n",
            "insertions": 52,
            "deletions": 28
          },
          {
            "hash": "bb1227406b05d05b4f4f980692b4dc0a04436c51",
            "messageTitle": "Translated using Weblate (Italian)",
            "messageBody": "Currently translated at 100.0% (50 of 50 strings)\n\nTranslation: OpenRefine/database\nTranslate-URL: https://hosted.weblate.org/projects/openrefine/database/it/\n",
            "insertions": 5,
            "deletions": 1
          },
          {
            "hash": "d50da67142b658612684f9b8989f1ccd1c80fe75",
            "messageTitle": "Translated using Weblate (Italian)",
            "messageBody": "Currently translated at 100.0% (158 of 158 strings)\n\nTranslation: OpenRefine/wikidata\nTranslate-URL: https://hosted.weblate.org/projects/openrefine/wikidata/it/\n",
            "insertions": 11,
            "deletions": 1
          },
          {
            "hash": "488a7021ff05628df6b22ef046b813aa255e6c9c",
            "messageTitle": "Translated using Weblate (Italian)",
            "messageBody": "Currently translated at 100.0% (44 of 44 strings)\n\nTranslation: OpenRefine/gdata\nTranslate-URL: https://hosted.weblate.org/projects/openrefine/gdata/it/\n",
            "insertions": 7,
            "deletions": 6
          }
        ]
      }
    ],
    "Negens": [
      {
        "insertions": 2,
        "deletions": 1,
        "date": "2020-01-08",
        "commitResults": [
          {
            "hash": "a4ee71a29d858ce94322d4d6e5af6b8ec3856e8c",
            "messageTitle": "Update the check_running() function in refine",
            "messageBody": "In strict shell environments, the \"$?\" is reset when evaluated.\r\nHere, the \"boolean if\" statements compares it to \"7\", then reset it and compares it to \"22\".\r\nIf the \"$?\" is intially \"22\", it is not evaluated and the NOT_RUNNING variable is ignored while it shouldn\u0027t. this leads to the error\r\n\"Something is already running on http://127.0.0.1:3333/\"\r\n\r\nTo avoid this, the solution is to first affect the value of \"$?\" to a non-system variable and then evaluate this new variable.",
            "insertions": 2,
            "deletions": 1
          }
        ]
      }
    ],
    "Thad Guidry": [
      {
        "insertions": 5,
        "deletions": 0,
        "date": "2020-01-08",
        "commitResults": [
          {
            "hash": "1d813917d728255eb0445a336cc54c6eafa93115",
            "messageTitle": "Create SUPPORT.md file",
            "messageBody": "This will add a special Github popup for first time issue creators, details of how it works are here: https://help.github.com/en/github/building-a-strong-community/adding-support-resources-to-your-project",
            "insertions": 5,
            "deletions": 0
          }
        ]
      }
    ]
  },
  "authorFinalContributionMap": {
    "Ederporto": 64,
    "Antonin Delpeuch": 377,
    "Hosted Weblate": 0,
    "Bhanu Gupta": 4,
    "jamessspanggg": 44,
    "Isao Matsunami": 3,
    "Luca Martinelli": 75,
    "Negens": 2,
    "Thad Guidry": 3
  },
  "authorFileTypeContributionMap": {
    "Ederporto": {
      "json": 64
    },
    "Antonin Delpeuch": {
      "md": 2,
      "js": 1,
      "vt": 4,
      "json": 3,
      "json": 1,
      "json": 1,
      "js": 6,
      "java": 15,
      "java": 1,
      "html": 4,
      "js": 29,
      "java": 6,
      "java": 2,
      "java": 7,
      "java": 1,
      "java": 8,
      "json": 1,
      "json": 1,
      "json": 1,
      "json": 1,
      "json": 1,
      "json": 1,
      "java": 6,
      "java": 3,
      "java": 1,
      "java": 41,
      "java": 36,
      "xml": 4,
      "java": 2,
      "java": 1,
      "java": 5,
      "java": 3,
      "java": 8,
      "java": 9,
      "java": 8,
      "java": 1,
      "java": 10,
      "java": 12,
      "java": 12,
      "java": 27,
      "java": 26,
      "js": 2,
      "js": 2,
      "js": 36,
      "js": 8,
      "js": 4,
      "js": 6,
      "xml": 7
    },
    "Hosted Weblate": {},
    "Bhanu Gupta": {
      "js": 4
    },
    "jamessspanggg": {
      "java": 4,
      "java": 39,
      "js": 1
    },
    "Isao Matsunami": {
      "json": 3
    },
    "Luca Martinelli": {
      "json": 5,
      "json": 7,
      "json": 11,
      "json": 52
    },
    "Negens": {
      "refine": 2
    },
    "Thad Guidry": {
      "md": 3
    }
  },
  "authorContributionVariance": {
    "Ederporto": 351.3102,
    "Antonin Delpeuch": 19668.533,
    "Hosted Weblate": 0.0,
    "Bhanu Gupta": 145.78055,
    "jamessspanggg": 65.00382,
    "Isao Matsunami": 0.8609694,
    "Luca Martinelli": 424.32013,
    "Negens": 0.30994895,
    "Thad Guidry": 0.8609694
  },
  "authorDisplayNameMap": {
    "Ederporto": "Ederporto",
    "Antonin Delpeuch": "Antonin Delpeuch",
    "Hosted Weblate": "Hosted Weblate",
    "Bhanu Gupta": "Bhanu Gupta",
    "jamessspanggg": "jamessspanggg",
    "Isao Matsunami": "Isao Matsunami",
    "Luca Martinelli": "Luca Martinelli",
    "Negens": "Negens",
    "Thad Guidry": "Thad Guidry"
  }
}
